octree_creation_app/__init__.py
octree_creation_app/constants.py
octree_creation_app/driver.py
octree_creation_app/params.py
octree_creation_app/utils.py
octree_creation_app-assets/__init__.py
octree_creation_app-assets/uijson/octree_mesh.ui.json
octree_creation_app-0.3.0.dist-info/LICENSE
octree_creation_app-0.3.0.dist-info/METADATA
octree_creation_app-0.3.0.dist-info/WHEEL
octree_creation_app-0.3.0.dist-info/RECORD
