Metadata-Version: 2.3
Name: octree-creation-app
Version: 0.3.0
Summary: Octree creation app.
License: MIT
Author: Mira Geoscience
Author-email: support@mirageoscience.com
Maintainer: Dominique Fournier
Maintainer-email: dominiquef@mirageoscience.com
Requires-Python: >=3.10,<4.0
Classifier: Development Status :: 4 - Beta
Classifier: Intended Audience :: Science/Research
Classifier: License :: OSI Approved :: MIT License
Classifier: Natural Language :: English
Classifier: Operating System :: MacOS
Classifier: Operating System :: Microsoft :: Windows
Classifier: Operating System :: POSIX
Classifier: Operating System :: Unix
Classifier: Programming Language :: Python
Classifier: Programming Language :: Python :: 3
Classifier: Programming Language :: Python :: 3.10
Classifier: Programming Language :: Python :: 3.11
Classifier: Programming Language :: Python :: 3.12
Classifier: Programming Language :: Python :: 3.13
Classifier: Topic :: Scientific/Engineering
Classifier: Topic :: Scientific/Engineering :: Mathematics
Classifier: Topic :: Scientific/Engineering :: Physics
Requires-Dist: discretize (==0.11.*)
Requires-Dist: geoapps-utils (>=0.5.0,<0.6.dev)
Requires-Dist: geoh5py (>=0.11.0,<0.12.dev)
Requires-Dist: numpy (>=1.26.0,<1.27.0)
Requires-Dist: pydantic (>=2.5.2,<3.0.0)
Requires-Dist: scipy (>=1.14.0,<1.15.0)
Project-URL: Documentation, https://mirageoscience-octree-creation-app.readthedocs-hosted.com/
Project-URL: Homepage, https://www.mirageoscience.com/mining-industry-software/python-integration/
Project-URL: Repository, https://github.com/MiraGeoscience/octree-creation-app
